fabricatio_yue/__init__.py
fabricatio_yue/cli.py
fabricatio_yue/config.py
fabricatio_yue/py.typed
fabricatio_yue/top_200_tags.json
fabricatio_yue/actions/__init__.py
fabricatio_yue/actions/compose.py
fabricatio_yue/capabilities/__init__.py
fabricatio_yue/capabilities/genre.py
fabricatio_yue/capabilities/lyricize.py
fabricatio_yue/models/__init__.py
fabricatio_yue/models/segment.py
fabricatio_yue/workflows/__init__.py
tests/test_genre_select.py
tests/test_segment.py
fabricatio_yue-0.2.12.dist-info/METADATA
fabricatio_yue-0.2.12.dist-info/WHEEL
fabricatio_yue-0.2.12.dist-info/entry_points.txt
fabricatio_yue-0.2.12.dist-info/licenses/LICENSE
fabricatio_yue-0.2.12.dist-info/RECORD
