Metadata-Version: 2.4
Name: fabricatio-yue
Version: 0.2.12
Summary: An extension of fabricatio, provide capability to compose lyrics that can be used in music generation with YuE.
Project-URL: Homepage, https://github.com/Whth/fabricatio
Project-URL: Repository, https://github.com/Whth/fabricatio
Project-URL: Issues, https://github.com/Whth/fabricatio/issues
Author-email: Whth <zettainspector@foxmail.com>
License: MIT License
License-File: LICENSE
Classifier: License :: OSI Approved :: MIT License
Classifier: Programming Language :: Python :: 3.12
Classifier: Programming Language :: Python :: 3.13
Classifier: Programming Language :: Python :: 3.14
Classifier: Programming Language :: Python :: Implementation :: CPython
Classifier: Typing :: Typed
Requires-Python: <3.15,>=3.12
Requires-Dist: fabricatio-core
Requires-Dist: more-itertools>=10.7.0
Requires-Dist: orjson>=3.11.4
Requires-Dist: pydantic>=2.11.5
Provides-Extra: cli
Requires-Dist: questionary>=2.1.0; extra == 'cli'
Requires-Dist: typer-slim[standard]>=0.15.2; extra == 'cli'
